MANIFEST.in
NEWS.txt
README.rst
setup.py
freeze_requirements.egg-info/PKG-INFO
freeze_requirements.egg-info/SOURCES.txt
freeze_requirements.egg-info/dependency_links.txt
freeze_requirements.egg-info/entry_points.txt
freeze_requirements.egg-info/not-zip-safe
freeze_requirements.egg-info/requires.txt
freeze_requirements.egg-info/top_level.txt
freezerequirements/__init__.py
freezerequirements/archive.py
freezerequirements/cli.py
freezerequirements/exceptions.py
freezerequirements/utils.py
freezerequirements/wheel_name.py
freezerequirements/tests/__init__.py
freezerequirements/tests/test_utils.py