Metadata-Version: 1.1
Name: freeze-requirements
Version: 0.4.6
Summary: A script to help creating and maintaining frozen requirements for pip
Home-page: https://github.com/Stupeflix/freeze-requirements
Author: Luper Rouch
Author-email: luper.rouch@gmail.com
License: BSD
Keywords: pip requirements frozen
Platform: UNKNOWN
Classifier: License :: OSI Approved :: BSD License
Classifier: Operating System :: POSIX
Classifier: Intended Audience :: Developers
Classifier: Topic :: Software Development :: Build Tools
Classifier: Topic :: System :: Software Distribution
